voluxcli/__init__.py
voluxcli/__version__.py
voluxcli/demos/__init__.py
voluxcli/demos/audio_demo.py
voluxcli/demos/basic_demo.py
voluxcli/demos/hue_demo.py
voluxcli/scripts/__init__.py
voluxcli/scripts/cli.py
voluxcli/scripts/paramtypes.py
voluxcli/scripts/util.py
voluxcli-0.3.1.dist-info/METADATA
voluxcli-0.3.1.dist-info/WHEEL
voluxcli-0.3.1.dist-info/entry_points.txt
voluxcli-0.3.1.dist-info/RECORD
