Metadata-Version: 2.1
Name: voluxcli
Version: 0.3.1
Summary: CLI for Volux
Home-page: https://gitlab.com/volux/volux
License: AGPLv3
Author: DrTexx
Author-email: denver.opensource@tutanota.com
Requires-Python: >=3.8,<4.0
Classifier: License :: Other/Proprietary License
Classifier: Programming Language :: Python :: 3
Classifier: Programming Language :: Python :: 3.8
Classifier: Programming Language :: Python :: 3.9
Classifier: Programming Language :: Python :: 3.10
Classifier: Programming Language :: Python :: 3.11
Requires-Dist: click (>=8.1.3,<9.0.0)
Requires-Dist: volux (>=0.10.0)
Project-URL: Repository, https://gitlab.com/volux/volux
